{"int":{"st":"ESERCIZIO","c_ele":7,"t_ele":"Regionali Speciali","f_elet":"VOTANTI","dt_ele":20251123000000,"l_terr":"REGIONE","area":"I","dt_agg":20251124151435},"note":["LA PERCENTUALE RIPORTATA NELLA COLONNA DELLA PRECEDENTE ELEZIONE E' SEMPRE RIFERITA A TUTTE LE SEZIONI DEL COMUNE."],"enti":{"ente_p":{"desc":"PUGLIA","cod":16,"ele_m":0,"ele_f":0,"ele_t":3527187,"com":[{"cod_reg":16,"com_att":4,"num_com":4}],"com_vot":[{"com":1,"dt_com":20251123120000,"enti_p":4032,"enti_t":4032,"perc":"8,55","vot_m":0,"vot_f":0,"vot_t":301421,"perc_r":"12,04"},{"com":2,"dt_com":20251123190000,"enti_p":4032,"enti_t":4032,"perc":"23,75","vot_m":0,"vot_f":0,"vot_t":837869,"perc_r":"27,60"},{"com":3,"dt_com":20251123230000,"enti_p":4032,"enti_t":4032,"perc":"29,45","vot_m":0,"vot_f":0,"vot_t":1038758,"perc_r":"39,88"},{"com":4,"dt_com":20251124150000,"enti_p":2859,"enti_t":4032,"perc":"42,37","vot_m":0,"vot_f":0,"vot_t":1068022,"perc_r":"56,90"}]},"enti_f":[{"tipo":"PROVINCIA","desc":"BARI","cod":9,"ele_m":0,"ele_f":0,"ele_t":1107116,"com_vot":[{"com":1,"dt_com":20251123120000,"enti_p":1224,"enti_t":1224,"perc":"9,00","vot_m":0,"vot_f":0,"vot_t":99638,"perc_r":"12,95"},{"com":2,"dt_com":20251123190000,"enti_p":1224,"enti_t":1224,"perc":"23,89","vot_m":0,"vot_f":0,"vot_t":264496,"perc_r":"29,20"},{"com":3,"dt_com":20251123230000,"enti_p":1224,"enti_t":1224,"perc":"30,09","vot_m":0,"vot_f":0,"vot_t":333180,"perc_r":"40,92"},{"com":4,"dt_com":20251124150000,"enti_p":891,"enti_t":1224,"perc":"42,88","vot_m":0,"vot_f":0,"vot_t":342878,"perc_r":"57,40"}]},{"tipo":"PROVINCIA","desc":"BARLETTA-ANDRIA-TRANI","cod":106,"ele_m":0,"ele_f":0,"ele_t":333006,"com_vot":[{"com":1,"dt_com":20251123120000,"enti_p":410,"enti_t":410,"perc":"8,52","vot_m":0,"vot_f":0,"vot_t":28357,"perc_r":"12,76"},{"com":2,"dt_com":20251123190000,"enti_p":410,"enti_t":410,"perc":"22,65","vot_m":0,"vot_f":0,"vot_t":75436,"perc_r":"29,72"},{"com":3,"dt_com":20251123230000,"enti_p":410,"enti_t":410,"perc":"28,81","vot_m":0,"vot_f":0,"vot_t":95946,"perc_r":"42,61"},{"com":4,"dt_com":20251124150000,"enti_p":347,"enti_t":410,"perc":"40,78","vot_m":0,"vot_f":0,"vot_t":114610,"perc_r":"59,98"}]},{"tipo":"PROVINCIA","desc":"BRINDISI","cod":16,"ele_m":0,"ele_f":0,"ele_t":345122,"com_vot":[{"com":1,"dt_com":20251123120000,"enti_p":378,"enti_t":378,"perc":"8,62","vot_m":0,"vot_f":0,"vot_t":29747,"perc_r":"11,53"},{"com":2,"dt_com":20251123190000,"enti_p":378,"enti_t":378,"perc":"24,33","vot_m":0,"vot_f":0,"vot_t":83963,"perc_r":"26,71"},{"com":3,"dt_com":20251123230000,"enti_p":378,"enti_t":378,"perc":"29,58","vot_m":0,"vot_f":0,"vot_t":102096,"perc_r":"38,71"},{"com":4,"dt_com":20251124150000,"enti_p":340,"enti_t":378,"perc":"41,14","vot_m":0,"vot_f":0,"vot_t":128223,"perc_r":"55,01"}]},{"tipo":"PROVINCIA","desc":"FOGGIA","cod":31,"ele_m":0,"ele_f":0,"ele_t":533219,"com_vot":[{"com":1,"dt_com":20251123120000,"enti_p":652,"enti_t":652,"perc":"7,18","vot_m":0,"vot_f":0,"vot_t":38301,"perc_r":"10,66"},{"com":2,"dt_com":20251123190000,"enti_p":652,"enti_t":652,"perc":"20,44","vot_m":0,"vot_f":0,"vot_t":108991,"perc_r":"25,03"},{"com":3,"dt_com":20251123230000,"enti_p":652,"enti_t":652,"perc":"26,15","vot_m":0,"vot_f":0,"vot_t":139463,"perc_r":"36,54"},{"com":4,"dt_com":20251124150000,"enti_p":316,"enti_t":652,"perc":"38,57","vot_m":0,"vot_f":0,"vot_t":99637,"perc_r":"53,37"}]},{"tipo":"PROVINCIA","desc":"LECCE","cod":41,"ele_m":0,"ele_f":0,"ele_t":725255,"com_vot":[{"com":1,"dt_com":20251123120000,"enti_p":825,"enti_t":825,"perc":"9,40","vot_m":0,"vot_f":0,"vot_t":68179,"perc_r":"12,18"},{"com":2,"dt_com":20251123190000,"enti_p":825,"enti_t":825,"perc":"27,33","vot_m":0,"vot_f":0,"vot_t":198207,"perc_r":"27,84"},{"com":3,"dt_com":20251123230000,"enti_p":825,"enti_t":825,"perc":"32,15","vot_m":0,"vot_f":0,"vot_t":233181,"perc_r":"41,04"},{"com":4,"dt_com":20251124150000,"enti_p":612,"enti_t":825,"perc":"44,31","vot_m":0,"vot_f":0,"vot_t":241064,"perc_r":"57,96"}]},{"tipo":"PROVINCIA","desc":"TARANTO","cod":78,"ele_m":0,"ele_f":0,"ele_t":483469,"com_vot":[{"com":1,"dt_com":20251123120000,"enti_p":543,"enti_t":543,"perc":"7,69","vot_m":0,"vot_f":0,"vot_t":37199,"perc_r":"11,23"},{"com":2,"dt_com":20251123190000,"enti_p":543,"enti_t":543,"perc":"22,09","vot_m":0,"vot_f":0,"vot_t":106776,"perc_r":"25,67"},{"com":3,"dt_com":20251123230000,"enti_p":543,"enti_t":543,"perc":"27,90","vot_m":0,"vot_f":0,"vot_t":134892,"perc_r":"38,53"},{"com":4,"dt_com":20251124150000,"enti_p":353,"enti_t":543,"perc":"43,40","vot_m":0,"vot_f":0,"vot_t":141610,"perc_r":"55,75"}]}]}}
