{"int":{"st":"ESERCIZIO","c_ele":7,"t_ele":"Regionali Speciali","f_elet":"VOTANTI","dt_ele":20251123000000,"l_terr":"PROVINCIA","area":"I","dt_agg":null},"note":["LA PERCENTUALE RIPORTATA NELLA COLONNA DELLA PRECEDENTE ELEZIONE E' SEMPRE RIFERITA A TUTTE LE SEZIONI DEL COMUNE."],"note_din":null,"enti":{"ente_p":{"desc":"LECCE","cod":41,"ele_m":0,"ele_f":0,"ele_t":725255,"com":[{"cod_reg":16,"com_att":0,"num_com":4}],"com_vot":[{"com":1,"dt_com":20251123120000,"enti_p":0,"enti_t":825,"perc":"0","vot_m":0,"vot_f":0,"vot_t":0,"perc_r":"0"},{"com":2,"dt_com":20251123190000,"enti_p":0,"enti_t":825,"perc":"0","vot_m":0,"vot_f":0,"vot_t":0,"perc_r":"0"},{"com":3,"dt_com":20251123230000,"enti_p":0,"enti_t":825,"perc":"0","vot_m":0,"vot_f":0,"vot_t":0,"perc_r":"0"},{"com":4,"dt_com":20251124150000,"enti_p":0,"enti_t":825,"perc":"0","vot_m":0,"vot_f":0,"vot_t":0,"perc_r":"0"}]},"enti_f":[{"tipo":"COMUNE","desc":"ALESSANO","cod":20,"ele_m":0,"ele_f":0,"ele_t":6199,"una_lis":null,"tipo_tras":"SZ","com_vot":[{"com":1,"dt_com":20251123120000,"enti_p":0,"enti_t":7,"perc":"0","vot_m":0,"vot_f":0,"vot_t":0,"perc_r":"0"},{"com":2,"dt_com":20251123190000,"enti_p":0,"enti_t":7,"perc":"0","vot_m":0,"vot_f":0,"vot_t":0,"perc_r":"0"},{"com":3,"dt_com":20251123230000,"enti_p":0,"enti_t":7,"perc":"0","vot_m":0,"vot_f":0,"vot_t":0,"perc_r":"0"},{"com":4,"dt_com":20251124150000,"enti_p":0,"enti_t":7,"perc":"0","vot_m":0,"vot_f":0,"vot_t":0,"perc_r":"0"}]},{"tipo":"COMUNE","desc":"ALEZIO","cod":30,"ele_m":0,"ele_f":0,"ele_t":5805,"una_lis":null,"tipo_tras":"SZ","com_vot":[{"com":1,"dt_com":20251123120000,"enti_p":0,"enti_t":5,"perc":"0","vot_m":0,"vot_f":0,"vot_t":0,"perc_r":"0"},{"com":2,"dt_com":20251123190000,"enti_p":0,"enti_t":5,"perc":"0","vot_m":0,"vot_f":0,"vot_t":0,"perc_r":"0"},{"com":3,"dt_com":20251123230000,"enti_p":0,"enti_t":5,"perc":"0","vot_m":0,"vot_f":0,"vot_t":0,"perc_r":"0"},{"com":4,"dt_com":20251124150000,"enti_p":0,"enti_t":5,"perc":"0","vot_m":0,"vot_f":0,"vot_t":0,"perc_r":"0"}]},{"tipo":"COMUNE","desc":"ALLISTE","cod":40,"ele_m":0,"ele_f":0,"ele_t":6523,"una_lis":null,"tipo_tras":"SZ","com_vot":[{"com":1,"dt_com":20251123120000,"enti_p":0,"enti_t":7,"perc":"0","vot_m":0,"vot_f":0,"vot_t":0,"perc_r":"0"},{"com":2,"dt_com":20251123190000,"enti_p":0,"enti_t":7,"perc":"0","vot_m":0,"vot_f":0,"vot_t":0,"perc_r":"0"},{"com":3,"dt_com":20251123230000,"enti_p":0,"enti_t":7,"perc":"0","vot_m":0,"vot_f":0,"vot_t":0,"perc_r":"0"},{"com":4,"dt_com":20251124150000,"enti_p":0,"enti_t":7,"perc":"0","vot_m":0,"vot_f":0,"vot_t":0,"perc_r":"0"}]},{"tipo":"COMUNE","desc":"ANDRANO","cod":50,"ele_m":0,"ele_f":0,"ele_t":4149,"una_lis":null,"tipo_tras":"SZ","com_vot":[{"com":1,"dt_com":20251123120000,"enti_p":0,"enti_t":5,"perc":"0","vot_m":0,"vot_f":0,"vot_t":0,"perc_r":"0"},{"com":2,"dt_com":20251123190000,"enti_p":0,"enti_t":5,"perc":"0","vot_m":0,"vot_f":0,"vot_t":0,"perc_r":"0"},{"com":3,"dt_com":20251123230000,"enti_p":0,"enti_t":5,"perc":"0","vot_m":0,"vot_f":0,"vot_t":0,"perc_r":"0"},{"com":4,"dt_com":20251124150000,"enti_p":0,"enti_t":5,"perc":"0","vot_m":0,"vot_f":0,"vot_t":0,"perc_r":"0"}]},{"tipo":"COMUNE","desc":"ARADEO","cod":60,"ele_m":0,"ele_f":0,"ele_t":9264,"una_lis":null,"tipo_tras":"SZ","com_vot":[{"com":1,"dt_com":20251123120000,"enti_p":0,"enti_t":9,"perc":"0","vot_m":0,"vot_f":0,"vot_t":0,"perc_r":"0"},{"com":2,"dt_com":20251123190000,"enti_p":0,"enti_t":9,"perc":"0","vot_m":0,"vot_f":0,"vot_t":0,"perc_r":"0"},{"com":3,"dt_com":20251123230000,"enti_p":0,"enti_t":9,"perc":"0","vot_m":0,"vot_f":0,"vot_t":0,"perc_r":"0"},{"com":4,"dt_com":20251124150000,"enti_p":0,"enti_t":9,"perc":"0","vot_m":0,"vot_f":0,"vot_t":0,"perc_r":"0"}]},{"tipo":"COMUNE","desc":"ARNESANO","cod":70,"ele_m":0,"ele_f":0,"ele_t":3433,"una_lis":null,"tipo_tras":"SZ","com_vot":[{"com":1,"dt_com":20251123120000,"enti_p":0,"enti_t":4,"perc":"0","vot_m":0,"vot_f":0,"vot_t":0,"perc_r":"0"},{"com":2,"dt_com":20251123190000,"enti_p":0,"enti_t":4,"perc":"0","vot_m":0,"vot_f":0,"vot_t":0,"perc_r":"0"},{"com":3,"dt_com":20251123230000,"enti_p":0,"enti_t":4,"perc":"0","vot_m":0,"vot_f":0,"vot_t":0,"perc_r":"0"},{"com":4,"dt_com":20251124150000,"enti_p":0,"enti_t":4,"perc":"0","vot_m":0,"vot_f":0,"vot_t":0,"perc_r":"0"}]},{"tipo":"COMUNE","desc":"BAGNOLO DEL SALENTO","cod":80,"ele_m":0,"ele_f":0,"ele_t":1770,"una_lis":null,"tipo_tras":"SZ","com_vot":[{"com":1,"dt_com":20251123120000,"enti_p":0,"enti_t":2,"perc":"0","vot_m":0,"vot_f":0,"vot_t":0,"perc_r":"0"},{"com":2,"dt_com":20251123190000,"enti_p":0,"enti_t":2,"perc":"0","vot_m":0,"vot_f":0,"vot_t":0,"perc_r":"0"},{"com":3,"dt_com":20251123230000,"enti_p":0,"enti_t":2,"perc":"0","vot_m":0,"vot_f":0,"vot_t":0,"perc_r":"0"},{"com":4,"dt_com":20251124150000,"enti_p":0,"enti_t":2,"perc":"0","vot_m":0,"vot_f":0,"vot_t":0,"perc_r":"0"}]},{"tipo":"COMUNE","desc":"BOTRUGNO","cod":81,"ele_m":0,"ele_f":0,"ele_t":2782,"una_lis":null,"tipo_tras":"SZ","com_vot":[{"com":1,"dt_com":20251123120000,"enti_p":0,"enti_t":3,"perc":"0","vot_m":0,"vot_f":0,"vot_t":0,"perc_r":"0"},{"com":2,"dt_com":20251123190000,"enti_p":0,"enti_t":3,"perc":"0","vot_m":0,"vot_f":0,"vot_t":0,"perc_r":"0"},{"com":3,"dt_com":20251123230000,"enti_p":0,"enti_t":3,"perc":"0","vot_m":0,"vot_f":0,"vot_t":0,"perc_r":"0"},{"com":4,"dt_com":20251124150000,"enti_p":0,"enti_t":3,"perc":"0","vot_m":0,"vot_f":0,"vot_t":0,"perc_r":"0"}]},{"tipo":"COMUNE","desc":"CALIMERA","cod":90,"ele_m":0,"ele_f":0,"ele_t":6121,"una_lis":null,"tipo_tras":"SZ","com_vot":[{"com":1,"dt_com":20251123120000,"enti_p":0,"enti_t":7,"perc":"0","vot_m":0,"vot_f":0,"vot_t":0,"perc_r":"0"},{"com":2,"dt_com":20251123190000,"enti_p":0,"enti_t":7,"perc":"0","vot_m":0,"vot_f":0,"vot_t":0,"perc_r":"0"},{"com":3,"dt_com":20251123230000,"enti_p":0,"enti_t":7,"perc":"0","vot_m":0,"vot_f":0,"vot_t":0,"perc_r":"0"},{"com":4,"dt_com":20251124150000,"enti_p":0,"enti_t":7,"perc":"0","vot_m":0,"vot_f":0,"vot_t":0,"perc_r":"0"}]},{"tipo":"COMUNE","desc":"CAMPI SALENTINA","cod":100,"ele_m":0,"ele_f":0,"ele_t":8789,"una_lis":null,"tipo_tras":"SZ","com_vot":[{"com":1,"dt_com":20251123120000,"enti_p":0,"enti_t":10,"perc":"0","vot_m":0,"vot_f":0,"vot_t":0,"perc_r":"0"},{"com":2,"dt_com":20251123190000,"enti_p":0,"enti_t":10,"perc":"0","vot_m":0,"vot_f":0,"vot_t":0,"perc_r":"0"},{"com":3,"dt_com":20251123230000,"enti_p":0,"enti_t":10,"perc":"0","vot_m":0,"vot_f":0,"vot_t":0,"perc_r":"0"},{"com":4,"dt_com":20251124150000,"enti_p":0,"enti_t":10,"perc":"0","vot_m":0,"vot_f":0,"vot_t":0,"perc_r":"0"}]},{"tipo":"COMUNE","desc":"CANNOLE","cod":110,"ele_m":0,"ele_f":0,"ele_t":1599,"una_lis":null,"tipo_tras":"SZ","com_vot":[{"com":1,"dt_com":20251123120000,"enti_p":0,"enti_t":2,"perc":"0","vot_m":0,"vot_f":0,"vot_t":0,"perc_r":"0"},{"com":2,"dt_com":20251123190000,"enti_p":0,"enti_t":2,"perc":"0","vot_m":0,"vot_f":0,"vot_t":0,"perc_r":"0"},{"com":3,"dt_com":20251123230000,"enti_p":0,"enti_t":2,"perc":"0","vot_m":0,"vot_f":0,"vot_t":0,"perc_r":"0"},{"com":4,"dt_com":20251124150000,"enti_p":0,"enti_t":2,"perc":"0","vot_m":0,"vot_f":0,"vot_t":0,"perc_r":"0"}]},{"tipo":"COMUNE","desc":"CAPRARICA DI LECCE","cod":120,"ele_m":0,"ele_f":0,"ele_t":2037,"una_lis":null,"tipo_tras":"SZ","com_vot":[{"com":1,"dt_com":20251123120000,"enti_p":0,"enti_t":3,"perc":"0","vot_m":0,"vot_f":0,"vot_t":0,"perc_r":"0"},{"com":2,"dt_com":20251123190000,"enti_p":0,"enti_t":3,"perc":"0","vot_m":0,"vot_f":0,"vot_t":0,"perc_r":"0"},{"com":3,"dt_com":20251123230000,"enti_p":0,"enti_t":3,"perc":"0","vot_m":0,"vot_f":0,"vot_t":0,"perc_r":"0"},{"com":4,"dt_com":20251124150000,"enti_p":0,"enti_t":3,"perc":"0","vot_m":0,"vot_f":0,"vot_t":0,"perc_r":"0"}]},{"tipo":"COMUNE","desc":"CARMIANO","cod":130,"ele_m":0,"ele_f":0,"ele_t":10391,"una_lis":null,"tipo_tras":"SZ","com_vot":[{"com":1,"dt_com":20251123120000,"enti_p":0,"enti_t":10,"perc":"0","vot_m":0,"vot_f":0,"vot_t":0,"perc_r":"0"},{"com":2,"dt_com":20251123190000,"enti_p":0,"enti_t":10,"perc":"0","vot_m":0,"vot_f":0,"vot_t":0,"perc_r":"0"},{"com":3,"dt_com":20251123230000,"enti_p":0,"enti_t":10,"perc":"0","vot_m":0,"vot_f":0,"vot_t":0,"perc_r":"0"},{"com":4,"dt_com":20251124150000,"enti_p":0,"enti_t":10,"perc":"0","vot_m":0,"vot_f":0,"vot_t":0,"perc_r":"0"}]},{"tipo":"COMUNE","desc":"CARPIGNANO SALENTINO","cod":140,"ele_m":0,"ele_f":0,"ele_t":3585,"una_lis":null,"tipo_tras":"SZ","com_vot":[{"com":1,"dt_com":20251123120000,"enti_p":0,"enti_t":5,"perc":"0","vot_m":0,"vot_f":0,"vot_t":0,"perc_r":"0"},{"com":2,"dt_com":20251123190000,"enti_p":0,"enti_t":5,"perc":"0","vot_m":0,"vot_f":0,"vot_t":0,"perc_r":"0"},{"com":3,"dt_com":20251123230000,"enti_p":0,"enti_t":5,"perc":"0","vot_m":0,"vot_f":0,"vot_t":0,"perc_r":"0"},{"com":4,"dt_com":20251124150000,"enti_p":0,"enti_t":5,"perc":"0","vot_m":0,"vot_f":0,"vot_t":0,"perc_r":"0"}]},{"tipo":"COMUNE","desc":"CASARANO","cod":150,"ele_m":0,"ele_f":0,"ele_t":18595,"una_lis":null,"tipo_tras":"SZ","com_vot":[{"com":1,"dt_com":20251123120000,"enti_p":0,"enti_t":23,"perc":"0","vot_m":0,"vot_f":0,"vot_t":0,"perc_r":"0"},{"com":2,"dt_com":20251123190000,"enti_p":0,"enti_t":23,"perc":"0","vot_m":0,"vot_f":0,"vot_t":0,"perc_r":"0"},{"com":3,"dt_com":20251123230000,"enti_p":0,"enti_t":23,"perc":"0","vot_m":0,"vot_f":0,"vot_t":0,"perc_r":"0"},{"com":4,"dt_com":20251124150000,"enti_p":0,"enti_t":23,"perc":"0","vot_m":0,"vot_f":0,"vot_t":0,"perc_r":"0"}]},{"tipo":"COMUNE","desc":"CASTRI DI LECCE","cod":160,"ele_m":0,"ele_f":0,"ele_t":2344,"una_lis":null,"tipo_tras":"SZ","com_vot":[{"com":1,"dt_com":20251123120000,"enti_p":0,"enti_t":3,"perc":"0","vot_m":0,"vot_f":0,"vot_t":0,"perc_r":"0"},{"com":2,"dt_com":20251123190000,"enti_p":0,"enti_t":3,"perc":"0","vot_m":0,"vot_f":0,"vot_t":0,"perc_r":"0"},{"com":3,"dt_com":20251123230000,"enti_p":0,"enti_t":3,"perc":"0","vot_m":0,"vot_f":0,"vot_t":0,"perc_r":"0"},{"com":4,"dt_com":20251124150000,"enti_p":0,"enti_t":3,"perc":"0","vot_m":0,"vot_f":0,"vot_t":0,"perc_r":"0"}]},{"tipo":"COMUNE","desc":"CASTRIGNANO DE' GRECI","cod":170,"ele_m":0,"ele_f":0,"ele_t":4168,"una_lis":null,"tipo_tras":"SZ","com_vot":[{"com":1,"dt_com":20251123120000,"enti_p":0,"enti_t":5,"perc":"0","vot_m":0,"vot_f":0,"vot_t":0,"perc_r":"0"},{"com":2,"dt_com":20251123190000,"enti_p":0,"enti_t":5,"perc":"0","vot_m":0,"vot_f":0,"vot_t":0,"perc_r":"0"},{"com":3,"dt_com":20251123230000,"enti_p":0,"enti_t":5,"perc":"0","vot_m":0,"vot_f":0,"vot_t":0,"perc_r":"0"},{"com":4,"dt_com":20251124150000,"enti_p":0,"enti_t":5,"perc":"0","vot_m":0,"vot_f":0,"vot_t":0,"perc_r":"0"}]},{"tipo":"COMUNE","desc":"CASTRIGNANO DEL CAPO","cod":180,"ele_m":0,"ele_f":0,"ele_t":5754,"una_lis":null,"tipo_tras":"SZ","com_vot":[{"com":1,"dt_com":20251123120000,"enti_p":0,"enti_t":6,"perc":"0","vot_m":0,"vot_f":0,"vot_t":0,"perc_r":"0"},{"com":2,"dt_com":20251123190000,"enti_p":0,"enti_t":6,"perc":"0","vot_m":0,"vot_f":0,"vot_t":0,"perc_r":"0"},{"com":3,"dt_com":20251123230000,"enti_p":0,"enti_t":6,"perc":"0","vot_m":0,"vot_f":0,"vot_t":0,"perc_r":"0"},{"com":4,"dt_com":20251124150000,"enti_p":0,"enti_t":6,"perc":"0","vot_m":0,"vot_f":0,"vot_t":0,"perc_r":"0"}]},{"tipo":"COMUNE","desc":"CASTRO","cod":181,"ele_m":0,"ele_f":0,"ele_t":2137,"una_lis":null,"tipo_tras":"SZ","com_vot":[{"com":1,"dt_com":20251123120000,"enti_p":0,"enti_t":3,"perc":"0","vot_m":0,"vot_f":0,"vot_t":0,"perc_r":"0"},{"com":2,"dt_com":20251123190000,"enti_p":0,"enti_t":3,"perc":"0","vot_m":0,"vot_f":0,"vot_t":0,"perc_r":"0"},{"com":3,"dt_com":20251123230000,"enti_p":0,"enti_t":3,"perc":"0","vot_m":0,"vot_f":0,"vot_t":0,"perc_r":"0"},{"com":4,"dt_com":20251124150000,"enti_p":0,"enti_t":3,"perc":"0","vot_m":0,"vot_f":0,"vot_t":0,"perc_r":"0"}]},{"tipo":"COMUNE","desc":"CAVALLINO","cod":190,"ele_m":0,"ele_f":0,"ele_t":11040,"una_lis":null,"tipo_tras":"SZ","com_vot":[{"com":1,"dt_com":20251123120000,"enti_p":0,"enti_t":10,"perc":"0","vot_m":0,"vot_f":0,"vot_t":0,"perc_r":"0"},{"com":2,"dt_com":20251123190000,"enti_p":0,"enti_t":10,"perc":"0","vot_m":0,"vot_f":0,"vot_t":0,"perc_r":"0"},{"com":3,"dt_com":20251123230000,"enti_p":0,"enti_t":10,"perc":"0","vot_m":0,"vot_f":0,"vot_t":0,"perc_r":"0"},{"com":4,"dt_com":20251124150000,"enti_p":0,"enti_t":10,"perc":"0","vot_m":0,"vot_f":0,"vot_t":0,"perc_r":"0"}]},{"tipo":"COMUNE","desc":"COLLEPASSO","cod":200,"ele_m":0,"ele_f":0,"ele_t":5776,"una_lis":null,"tipo_tras":"SZ","com_vot":[{"com":1,"dt_com":20251123120000,"enti_p":0,"enti_t":6,"perc":"0","vot_m":0,"vot_f":0,"vot_t":0,"perc_r":"0"},{"com":2,"dt_com":20251123190000,"enti_p":0,"enti_t":6,"perc":"0","vot_m":0,"vot_f":0,"vot_t":0,"perc_r":"0"},{"com":3,"dt_com":20251123230000,"enti_p":0,"enti_t":6,"perc":"0","vot_m":0,"vot_f":0,"vot_t":0,"perc_r":"0"},{"com":4,"dt_com":20251124150000,"enti_p":0,"enti_t":6,"perc":"0","vot_m":0,"vot_f":0,"vot_t":0,"perc_r":"0"}]},{"tipo":"COMUNE","desc":"COPERTINO","cod":210,"ele_m":0,"ele_f":0,"ele_t":21269,"una_lis":null,"tipo_tras":"SZ","com_vot":[{"com":1,"dt_com":20251123120000,"enti_p":0,"enti_t":26,"perc":"0","vot_m":0,"vot_f":0,"vot_t":0,"perc_r":"0"},{"com":2,"dt_com":20251123190000,"enti_p":0,"enti_t":26,"perc":"0","vot_m":0,"vot_f":0,"vot_t":0,"perc_r":"0"},{"com":3,"dt_com":20251123230000,"enti_p":0,"enti_t":26,"perc":"0","vot_m":0,"vot_f":0,"vot_t":0,"perc_r":"0"},{"com":4,"dt_com":20251124150000,"enti_p":0,"enti_t":26,"perc":"0","vot_m":0,"vot_f":0,"vot_t":0,"perc_r":"0"}]},{"tipo":"COMUNE","desc":"CORIGLIANO D'OTRANTO","cod":220,"ele_m":0,"ele_f":0,"ele_t":5602,"una_lis":null,"tipo_tras":"SZ","com_vot":[{"com":1,"dt_com":20251123120000,"enti_p":0,"enti_t":5,"perc":"0","vot_m":0,"vot_f":0,"vot_t":0,"perc_r":"0"},{"com":2,"dt_com":20251123190000,"enti_p":0,"enti_t":5,"perc":"0","vot_m":0,"vot_f":0,"vot_t":0,"perc_r":"0"},{"com":3,"dt_com":20251123230000,"enti_p":0,"enti_t":5,"perc":"0","vot_m":0,"vot_f":0,"vot_t":0,"perc_r":"0"},{"com":4,"dt_com":20251124150000,"enti_p":0,"enti_t":5,"perc":"0","vot_m":0,"vot_f":0,"vot_t":0,"perc_r":"0"}]},{"tipo":"COMUNE","desc":"CORSANO","cod":230,"ele_m":0,"ele_f":0,"ele_t":4889,"una_lis":null,"tipo_tras":"SZ","com_vot":[{"com":1,"dt_com":20251123120000,"enti_p":0,"enti_t":5,"perc":"0","vot_m":0,"vot_f":0,"vot_t":0,"perc_r":"0"},{"com":2,"dt_com":20251123190000,"enti_p":0,"enti_t":5,"perc":"0","vot_m":0,"vot_f":0,"vot_t":0,"perc_r":"0"},{"com":3,"dt_com":20251123230000,"enti_p":0,"enti_t":5,"perc":"0","vot_m":0,"vot_f":0,"vot_t":0,"perc_r":"0"},{"com":4,"dt_com":20251124150000,"enti_p":0,"enti_t":5,"perc":"0","vot_m":0,"vot_f":0,"vot_t":0,"perc_r":"0"}]},{"tipo":"COMUNE","desc":"CURSI","cod":240,"ele_m":0,"ele_f":0,"ele_t":3644,"una_lis":null,"tipo_tras":"SZ","com_vot":[{"com":1,"dt_com":20251123120000,"enti_p":0,"enti_t":4,"perc":"0","vot_m":0,"vot_f":0,"vot_t":0,"perc_r":"0"},{"com":2,"dt_com":20251123190000,"enti_p":0,"enti_t":4,"perc":"0","vot_m":0,"vot_f":0,"vot_t":0,"perc_r":"0"},{"com":3,"dt_com":20251123230000,"enti_p":0,"enti_t":4,"perc":"0","vot_m":0,"vot_f":0,"vot_t":0,"perc_r":"0"},{"com":4,"dt_com":20251124150000,"enti_p":0,"enti_t":4,"perc":"0","vot_m":0,"vot_f":0,"vot_t":0,"perc_r":"0"}]},{"tipo":"COMUNE","desc":"CUTROFIANO","cod":250,"ele_m":0,"ele_f":0,"ele_t":8215,"una_lis":null,"tipo_tras":"SZ","com_vot":[{"com":1,"dt_com":20251123120000,"enti_p":0,"enti_t":9,"perc":"0","vot_m":0,"vot_f":0,"vot_t":0,"perc_r":"0"},{"com":2,"dt_com":20251123190000,"enti_p":0,"enti_t":9,"perc":"0","vot_m":0,"vot_f":0,"vot_t":0,"perc_r":"0"},{"com":3,"dt_com":20251123230000,"enti_p":0,"enti_t":9,"perc":"0","vot_m":0,"vot_f":0,"vot_t":0,"perc_r":"0"},{"com":4,"dt_com":20251124150000,"enti_p":0,"enti_t":9,"perc":"0","vot_m":0,"vot_f":0,"vot_t":0,"perc_r":"0"}]},{"tipo":"COMUNE","desc":"DISO","cod":260,"ele_m":0,"ele_f":0,"ele_t":2698,"una_lis":null,"tipo_tras":"SZ","com_vot":[{"com":1,"dt_com":20251123120000,"enti_p":0,"enti_t":3,"perc":"0","vot_m":0,"vot_f":0,"vot_t":0,"perc_r":"0"},{"com":2,"dt_com":20251123190000,"enti_p":0,"enti_t":3,"perc":"0","vot_m":0,"vot_f":0,"vot_t":0,"perc_r":"0"},{"com":3,"dt_com":20251123230000,"enti_p":0,"enti_t":3,"perc":"0","vot_m":0,"vot_f":0,"vot_t":0,"perc_r":"0"},{"com":4,"dt_com":20251124150000,"enti_p":0,"enti_t":3,"perc":"0","vot_m":0,"vot_f":0,"vot_t":0,"perc_r":"0"}]},{"tipo":"COMUNE","desc":"GAGLIANO DEL CAPO","cod":270,"ele_m":0,"ele_f":0,"ele_t":5473,"una_lis":null,"tipo_tras":"SZ","com_vot":[{"com":1,"dt_com":20251123120000,"enti_p":0,"enti_t":5,"perc":"0","vot_m":0,"vot_f":0,"vot_t":0,"perc_r":"0"},{"com":2,"dt_com":20251123190000,"enti_p":0,"enti_t":5,"perc":"0","vot_m":0,"vot_f":0,"vot_t":0,"perc_r":"0"},{"com":3,"dt_com":20251123230000,"enti_p":0,"enti_t":5,"perc":"0","vot_m":0,"vot_f":0,"vot_t":0,"perc_r":"0"},{"com":4,"dt_com":20251124150000,"enti_p":0,"enti_t":5,"perc":"0","vot_m":0,"vot_f":0,"vot_t":0,"perc_r":"0"}]},{"tipo":"COMUNE","desc":"GALATINA","cod":280,"ele_m":0,"ele_f":0,"ele_t":23197,"una_lis":null,"tipo_tras":"SZ","com_vot":[{"com":1,"dt_com":20251123120000,"enti_p":0,"enti_t":28,"perc":"0","vot_m":0,"vot_f":0,"vot_t":0,"perc_r":"0"},{"com":2,"dt_com":20251123190000,"enti_p":0,"enti_t":28,"perc":"0","vot_m":0,"vot_f":0,"vot_t":0,"perc_r":"0"},{"com":3,"dt_com":20251123230000,"enti_p":0,"enti_t":28,"perc":"0","vot_m":0,"vot_f":0,"vot_t":0,"perc_r":"0"},{"com":4,"dt_com":20251124150000,"enti_p":0,"enti_t":28,"perc":"0","vot_m":0,"vot_f":0,"vot_t":0,"perc_r":"0"}]},{"tipo":"COMUNE","desc":"GALATONE","cod":290,"ele_m":0,"ele_f":0,"ele_t":14826,"una_lis":null,"tipo_tras":"SZ","com_vot":[{"com":1,"dt_com":20251123120000,"enti_p":0,"enti_t":15,"perc":"0","vot_m":0,"vot_f":0,"vot_t":0,"perc_r":"0"},{"com":2,"dt_com":20251123190000,"enti_p":0,"enti_t":15,"perc":"0","vot_m":0,"vot_f":0,"vot_t":0,"perc_r":"0"},{"com":3,"dt_com":20251123230000,"enti_p":0,"enti_t":15,"perc":"0","vot_m":0,"vot_f":0,"vot_t":0,"perc_r":"0"},{"com":4,"dt_com":20251124150000,"enti_p":0,"enti_t":15,"perc":"0","vot_m":0,"vot_f":0,"vot_t":0,"perc_r":"0"}]},{"tipo":"COMUNE","desc":"GALLIPOLI","cod":300,"ele_m":0,"ele_f":0,"ele_t":19582,"una_lis":null,"tipo_tras":"SZ","com_vot":[{"com":1,"dt_com":20251123120000,"enti_p":0,"enti_t":24,"perc":"0","vot_m":0,"vot_f":0,"vot_t":0,"perc_r":"0"},{"com":2,"dt_com":20251123190000,"enti_p":0,"enti_t":24,"perc":"0","vot_m":0,"vot_f":0,"vot_t":0,"perc_r":"0"},{"com":3,"dt_com":20251123230000,"enti_p":0,"enti_t":24,"perc":"0","vot_m":0,"vot_f":0,"vot_t":0,"perc_r":"0"},{"com":4,"dt_com":20251124150000,"enti_p":0,"enti_t":24,"perc":"0","vot_m":0,"vot_f":0,"vot_t":0,"perc_r":"0"}]},{"tipo":"COMUNE","desc":"GIUGGIANELLO","cod":310,"ele_m":0,"ele_f":0,"ele_t":1059,"una_lis":null,"tipo_tras":"SZ","com_vot":[{"com":1,"dt_com":20251123120000,"enti_p":0,"enti_t":1,"perc":"0","vot_m":0,"vot_f":0,"vot_t":0,"perc_r":"0"},{"com":2,"dt_com":20251123190000,"enti_p":0,"enti_t":1,"perc":"0","vot_m":0,"vot_f":0,"vot_t":0,"perc_r":"0"},{"com":3,"dt_com":20251123230000,"enti_p":0,"enti_t":1,"perc":"0","vot_m":0,"vot_f":0,"vot_t":0,"perc_r":"0"},{"com":4,"dt_com":20251124150000,"enti_p":0,"enti_t":1,"perc":"0","vot_m":0,"vot_f":0,"vot_t":0,"perc_r":"0"}]},{"tipo":"COMUNE","desc":"GIURDIGNANO","cod":320,"ele_m":0,"ele_f":0,"ele_t":1784,"una_lis":null,"tipo_tras":"SZ","com_vot":[{"com":1,"dt_com":20251123120000,"enti_p":0,"enti_t":2,"perc":"0","vot_m":0,"vot_f":0,"vot_t":0,"perc_r":"0"},{"com":2,"dt_com":20251123190000,"enti_p":0,"enti_t":2,"perc":"0","vot_m":0,"vot_f":0,"vot_t":0,"perc_r":"0"},{"com":3,"dt_com":20251123230000,"enti_p":0,"enti_t":2,"perc":"0","vot_m":0,"vot_f":0,"vot_t":0,"perc_r":"0"},{"com":4,"dt_com":20251124150000,"enti_p":0,"enti_t":2,"perc":"0","vot_m":0,"vot_f":0,"vot_t":0,"perc_r":"0"}]},{"tipo":"COMUNE","desc":"GUAGNANO","cod":330,"ele_m":0,"ele_f":0,"ele_t":5191,"una_lis":null,"tipo_tras":"SZ","com_vot":[{"com":1,"dt_com":20251123120000,"enti_p":0,"enti_t":6,"perc":"0","vot_m":0,"vot_f":0,"vot_t":0,"perc_r":"0"},{"com":2,"dt_com":20251123190000,"enti_p":0,"enti_t":6,"perc":"0","vot_m":0,"vot_f":0,"vot_t":0,"perc_r":"0"},{"com":3,"dt_com":20251123230000,"enti_p":0,"enti_t":6,"perc":"0","vot_m":0,"vot_f":0,"vot_t":0,"perc_r":"0"},{"com":4,"dt_com":20251124150000,"enti_p":0,"enti_t":6,"perc":"0","vot_m":0,"vot_f":0,"vot_t":0,"perc_r":"0"}]},{"tipo":"COMUNE","desc":"LECCE","cod":340,"ele_m":0,"ele_f":0,"ele_t":77939,"una_lis":null,"tipo_tras":"SZ","com_vot":[{"com":1,"dt_com":20251123120000,"enti_p":0,"enti_t":102,"perc":"0","vot_m":0,"vot_f":0,"vot_t":0,"perc_r":"0"},{"com":2,"dt_com":20251123190000,"enti_p":0,"enti_t":102,"perc":"0","vot_m":0,"vot_f":0,"vot_t":0,"perc_r":"0"},{"com":3,"dt_com":20251123230000,"enti_p":0,"enti_t":102,"perc":"0","vot_m":0,"vot_f":0,"vot_t":0,"perc_r":"0"},{"com":4,"dt_com":20251124150000,"enti_p":0,"enti_t":102,"perc":"0","vot_m":0,"vot_f":0,"vot_t":0,"perc_r":"0"}]},{"tipo":"COMUNE","desc":"LEQUILE","cod":350,"ele_m":0,"ele_f":0,"ele_t":7252,"una_lis":null,"tipo_tras":"SZ","com_vot":[{"com":1,"dt_com":20251123120000,"enti_p":0,"enti_t":7,"perc":"0","vot_m":0,"vot_f":0,"vot_t":0,"perc_r":"0"},{"com":2,"dt_com":20251123190000,"enti_p":0,"enti_t":7,"perc":"0","vot_m":0,"vot_f":0,"vot_t":0,"perc_r":"0"},{"com":3,"dt_com":20251123230000,"enti_p":0,"enti_t":7,"perc":"0","vot_m":0,"vot_f":0,"vot_t":0,"perc_r":"0"},{"com":4,"dt_com":20251124150000,"enti_p":0,"enti_t":7,"perc":"0","vot_m":0,"vot_f":0,"vot_t":0,"perc_r":"0"}]},{"tipo":"COMUNE","desc":"LEVERANO","cod":360,"ele_m":0,"ele_f":0,"ele_t":11925,"una_lis":null,"tipo_tras":"SZ","com_vot":[{"com":1,"dt_com":20251123120000,"enti_p":0,"enti_t":12,"perc":"0","vot_m":0,"vot_f":0,"vot_t":0,"perc_r":"0"},{"com":2,"dt_com":20251123190000,"enti_p":0,"enti_t":12,"perc":"0","vot_m":0,"vot_f":0,"vot_t":0,"perc_r":"0"},{"com":3,"dt_com":20251123230000,"enti_p":0,"enti_t":12,"perc":"0","vot_m":0,"vot_f":0,"vot_t":0,"perc_r":"0"},{"com":4,"dt_com":20251124150000,"enti_p":0,"enti_t":12,"perc":"0","vot_m":0,"vot_f":0,"vot_t":0,"perc_r":"0"}]},{"tipo":"COMUNE","desc":"LIZZANELLO","cod":370,"ele_m":0,"ele_f":0,"ele_t":10013,"una_lis":null,"tipo_tras":"SZ","com_vot":[{"com":1,"dt_com":20251123120000,"enti_p":0,"enti_t":11,"perc":"0","vot_m":0,"vot_f":0,"vot_t":0,"perc_r":"0"},{"com":2,"dt_com":20251123190000,"enti_p":0,"enti_t":11,"perc":"0","vot_m":0,"vot_f":0,"vot_t":0,"perc_r":"0"},{"com":3,"dt_com":20251123230000,"enti_p":0,"enti_t":11,"perc":"0","vot_m":0,"vot_f":0,"vot_t":0,"perc_r":"0"},{"com":4,"dt_com":20251124150000,"enti_p":0,"enti_t":11,"perc":"0","vot_m":0,"vot_f":0,"vot_t":0,"perc_r":"0"}]},{"tipo":"COMUNE","desc":"MAGLIE","cod":380,"ele_m":0,"ele_f":0,"ele_t":12400,"una_lis":null,"tipo_tras":"SZ","com_vot":[{"com":1,"dt_com":20251123120000,"enti_p":0,"enti_t":17,"perc":"0","vot_m":0,"vot_f":0,"vot_t":0,"perc_r":"0"},{"com":2,"dt_com":20251123190000,"enti_p":0,"enti_t":17,"perc":"0","vot_m":0,"vot_f":0,"vot_t":0,"perc_r":"0"},{"com":3,"dt_com":20251123230000,"enti_p":0,"enti_t":17,"perc":"0","vot_m":0,"vot_f":0,"vot_t":0,"perc_r":"0"},{"com":4,"dt_com":20251124150000,"enti_p":0,"enti_t":17,"perc":"0","vot_m":0,"vot_f":0,"vot_t":0,"perc_r":"0"}]},{"tipo":"COMUNE","desc":"MARTANO","cod":390,"ele_m":0,"ele_f":0,"ele_t":8683,"una_lis":null,"tipo_tras":"SZ","com_vot":[{"com":1,"dt_com":20251123120000,"enti_p":0,"enti_t":10,"perc":"0","vot_m":0,"vot_f":0,"vot_t":0,"perc_r":"0"},{"com":2,"dt_com":20251123190000,"enti_p":0,"enti_t":10,"perc":"0","vot_m":0,"vot_f":0,"vot_t":0,"perc_r":"0"},{"com":3,"dt_com":20251123230000,"enti_p":0,"enti_t":10,"perc":"0","vot_m":0,"vot_f":0,"vot_t":0,"perc_r":"0"},{"com":4,"dt_com":20251124150000,"enti_p":0,"enti_t":10,"perc":"0","vot_m":0,"vot_f":0,"vot_t":0,"perc_r":"0"}]},{"tipo":"COMUNE","desc":"MARTIGNANO","cod":400,"ele_m":0,"ele_f":0,"ele_t":1411,"una_lis":null,"tipo_tras":"SZ","com_vot":[{"com":1,"dt_com":20251123120000,"enti_p":0,"enti_t":2,"perc":"0","vot_m":0,"vot_f":0,"vot_t":0,"perc_r":"0"},{"com":2,"dt_com":20251123190000,"enti_p":0,"enti_t":2,"perc":"0","vot_m":0,"vot_f":0,"vot_t":0,"perc_r":"0"},{"com":3,"dt_com":20251123230000,"enti_p":0,"enti_t":2,"perc":"0","vot_m":0,"vot_f":0,"vot_t":0,"perc_r":"0"},{"com":4,"dt_com":20251124150000,"enti_p":0,"enti_t":2,"perc":"0","vot_m":0,"vot_f":0,"vot_t":0,"perc_r":"0"}]},{"tipo":"COMUNE","desc":"MATINO","cod":410,"ele_m":0,"ele_f":0,"ele_t":11110,"una_lis":null,"tipo_tras":"SZ","com_vot":[{"com":1,"dt_com":20251123120000,"enti_p":0,"enti_t":12,"perc":"0","vot_m":0,"vot_f":0,"vot_t":0,"perc_r":"0"},{"com":2,"dt_com":20251123190000,"enti_p":0,"enti_t":12,"perc":"0","vot_m":0,"vot_f":0,"vot_t":0,"perc_r":"0"},{"com":3,"dt_com":20251123230000,"enti_p":0,"enti_t":12,"perc":"0","vot_m":0,"vot_f":0,"vot_t":0,"perc_r":"0"},{"com":4,"dt_com":20251124150000,"enti_p":0,"enti_t":12,"perc":"0","vot_m":0,"vot_f":0,"vot_t":0,"perc_r":"0"}]},{"tipo":"COMUNE","desc":"MELENDUGNO","cod":420,"ele_m":0,"ele_f":0,"ele_t":9257,"una_lis":null,"tipo_tras":"SZ","com_vot":[{"com":1,"dt_com":20251123120000,"enti_p":0,"enti_t":8,"perc":"0","vot_m":0,"vot_f":0,"vot_t":0,"perc_r":"0"},{"com":2,"dt_com":20251123190000,"enti_p":0,"enti_t":8,"perc":"0","vot_m":0,"vot_f":0,"vot_t":0,"perc_r":"0"},{"com":3,"dt_com":20251123230000,"enti_p":0,"enti_t":8,"perc":"0","vot_m":0,"vot_f":0,"vot_t":0,"perc_r":"0"},{"com":4,"dt_com":20251124150000,"enti_p":0,"enti_t":8,"perc":"0","vot_m":0,"vot_f":0,"vot_t":0,"perc_r":"0"}]},{"tipo":"COMUNE","desc":"MELISSANO","cod":430,"ele_m":0,"ele_f":0,"ele_t":6398,"una_lis":null,"tipo_tras":"SZ","com_vot":[{"com":1,"dt_com":20251123120000,"enti_p":0,"enti_t":7,"perc":"0","vot_m":0,"vot_f":0,"vot_t":0,"perc_r":"0"},{"com":2,"dt_com":20251123190000,"enti_p":0,"enti_t":7,"perc":"0","vot_m":0,"vot_f":0,"vot_t":0,"perc_r":"0"},{"com":3,"dt_com":20251123230000,"enti_p":0,"enti_t":7,"perc":"0","vot_m":0,"vot_f":0,"vot_t":0,"perc_r":"0"},{"com":4,"dt_com":20251124150000,"enti_p":0,"enti_t":7,"perc":"0","vot_m":0,"vot_f":0,"vot_t":0,"perc_r":"0"}]},{"tipo":"COMUNE","desc":"MELPIGNANO","cod":440,"ele_m":0,"ele_f":0,"ele_t":2399,"una_lis":null,"tipo_tras":"SZ","com_vot":[{"com":1,"dt_com":20251123120000,"enti_p":0,"enti_t":3,"perc":"0","vot_m":0,"vot_f":0,"vot_t":0,"perc_r":"0"},{"com":2,"dt_com":20251123190000,"enti_p":0,"enti_t":3,"perc":"0","vot_m":0,"vot_f":0,"vot_t":0,"perc_r":"0"},{"com":3,"dt_com":20251123230000,"enti_p":0,"enti_t":3,"perc":"0","vot_m":0,"vot_f":0,"vot_t":0,"perc_r":"0"},{"com":4,"dt_com":20251124150000,"enti_p":0,"enti_t":3,"perc":"0","vot_m":0,"vot_f":0,"vot_t":0,"perc_r":"0"}]},{"tipo":"COMUNE","desc":"MIGGIANO","cod":450,"ele_m":0,"ele_f":0,"ele_t":3134,"una_lis":null,"tipo_tras":"SZ","com_vot":[{"com":1,"dt_com":20251123120000,"enti_p":0,"enti_t":3,"perc":"0","vot_m":0,"vot_f":0,"vot_t":0,"perc_r":"0"},{"com":2,"dt_com":20251123190000,"enti_p":0,"enti_t":3,"perc":"0","vot_m":0,"vot_f":0,"vot_t":0,"perc_r":"0"},{"com":3,"dt_com":20251123230000,"enti_p":0,"enti_t":3,"perc":"0","vot_m":0,"vot_f":0,"vot_t":0,"perc_r":"0"},{"com":4,"dt_com":20251124150000,"enti_p":0,"enti_t":3,"perc":"0","vot_m":0,"vot_f":0,"vot_t":0,"perc_r":"0"}]},{"tipo":"COMUNE","desc":"MINERVINO DI LECCE","cod":460,"ele_m":0,"ele_f":0,"ele_t":3504,"una_lis":null,"tipo_tras":"SZ","com_vot":[{"com":1,"dt_com":20251123120000,"enti_p":0,"enti_t":4,"perc":"0","vot_m":0,"vot_f":0,"vot_t":0,"perc_r":"0"},{"com":2,"dt_com":20251123190000,"enti_p":0,"enti_t":4,"perc":"0","vot_m":0,"vot_f":0,"vot_t":0,"perc_r":"0"},{"com":3,"dt_com":20251123230000,"enti_p":0,"enti_t":4,"perc":"0","vot_m":0,"vot_f":0,"vot_t":0,"perc_r":"0"},{"com":4,"dt_com":20251124150000,"enti_p":0,"enti_t":4,"perc":"0","vot_m":0,"vot_f":0,"vot_t":0,"perc_r":"0"}]},{"tipo":"COMUNE","desc":"MONTERONI DI LECCE","cod":470,"ele_m":0,"ele_f":0,"ele_t":11496,"una_lis":null,"tipo_tras":"SZ","com_vot":[{"com":1,"dt_com":20251123120000,"enti_p":0,"enti_t":11,"perc":"0","vot_m":0,"vot_f":0,"vot_t":0,"perc_r":"0"},{"com":2,"dt_com":20251123190000,"enti_p":0,"enti_t":11,"perc":"0","vot_m":0,"vot_f":0,"vot_t":0,"perc_r":"0"},{"com":3,"dt_com":20251123230000,"enti_p":0,"enti_t":11,"perc":"0","vot_m":0,"vot_f":0,"vot_t":0,"perc_r":"0"},{"com":4,"dt_com":20251124150000,"enti_p":0,"enti_t":11,"perc":"0","vot_m":0,"vot_f":0,"vot_t":0,"perc_r":"0"}]},{"tipo":"COMUNE","desc":"MONTESANO SALENTINO","cod":480,"ele_m":0,"ele_f":0,"ele_t":2302,"una_lis":null,"tipo_tras":"SZ","com_vot":[{"com":1,"dt_com":20251123120000,"enti_p":0,"enti_t":3,"perc":"0","vot_m":0,"vot_f":0,"vot_t":0,"perc_r":"0"},{"com":2,"dt_com":20251123190000,"enti_p":0,"enti_t":3,"perc":"0","vot_m":0,"vot_f":0,"vot_t":0,"perc_r":"0"},{"com":3,"dt_com":20251123230000,"enti_p":0,"enti_t":3,"perc":"0","vot_m":0,"vot_f":0,"vot_t":0,"perc_r":"0"},{"com":4,"dt_com":20251124150000,"enti_p":0,"enti_t":3,"perc":"0","vot_m":0,"vot_f":0,"vot_t":0,"perc_r":"0"}]},{"tipo":"COMUNE","desc":"MORCIANO DI LEUCA","cod":490,"ele_m":0,"ele_f":0,"ele_t":3891,"una_lis":null,"tipo_tras":"SZ","com_vot":[{"com":1,"dt_com":20251123120000,"enti_p":0,"enti_t":4,"perc":"0","vot_m":0,"vot_f":0,"vot_t":0,"perc_r":"0"},{"com":2,"dt_com":20251123190000,"enti_p":0,"enti_t":4,"perc":"0","vot_m":0,"vot_f":0,"vot_t":0,"perc_r":"0"},{"com":3,"dt_com":20251123230000,"enti_p":0,"enti_t":4,"perc":"0","vot_m":0,"vot_f":0,"vot_t":0,"perc_r":"0"},{"com":4,"dt_com":20251124150000,"enti_p":0,"enti_t":4,"perc":"0","vot_m":0,"vot_f":0,"vot_t":0,"perc_r":"0"}]},{"tipo":"COMUNE","desc":"MURO LECCESE","cod":500,"ele_m":0,"ele_f":0,"ele_t":4525,"una_lis":null,"tipo_tras":"SZ","com_vot":[{"com":1,"dt_com":20251123120000,"enti_p":0,"enti_t":5,"perc":"0","vot_m":0,"vot_f":0,"vot_t":0,"perc_r":"0"},{"com":2,"dt_com":20251123190000,"enti_p":0,"enti_t":5,"perc":"0","vot_m":0,"vot_f":0,"vot_t":0,"perc_r":"0"},{"com":3,"dt_com":20251123230000,"enti_p":0,"enti_t":5,"perc":"0","vot_m":0,"vot_f":0,"vot_t":0,"perc_r":"0"},{"com":4,"dt_com":20251124150000,"enti_p":0,"enti_t":5,"perc":"0","vot_m":0,"vot_f":0,"vot_t":0,"perc_r":"0"}]},{"tipo":"COMUNE","desc":"NARDO'","cod":510,"ele_m":0,"ele_f":0,"ele_t":29844,"una_lis":null,"tipo_tras":"SZ","com_vot":[{"com":1,"dt_com":20251123120000,"enti_p":0,"enti_t":33,"perc":"0","vot_m":0,"vot_f":0,"vot_t":0,"perc_r":"0"},{"com":2,"dt_com":20251123190000,"enti_p":0,"enti_t":33,"perc":"0","vot_m":0,"vot_f":0,"vot_t":0,"perc_r":"0"},{"com":3,"dt_com":20251123230000,"enti_p":0,"enti_t":33,"perc":"0","vot_m":0,"vot_f":0,"vot_t":0,"perc_r":"0"},{"com":4,"dt_com":20251124150000,"enti_p":0,"enti_t":33,"perc":"0","vot_m":0,"vot_f":0,"vot_t":0,"perc_r":"0"}]},{"tipo":"COMUNE","desc":"NEVIANO","cod":520,"ele_m":0,"ele_f":0,"ele_t":5134,"una_lis":null,"tipo_tras":"SZ","com_vot":[{"com":1,"dt_com":20251123120000,"enti_p":0,"enti_t":5,"perc":"0","vot_m":0,"vot_f":0,"vot_t":0,"perc_r":"0"},{"com":2,"dt_com":20251123190000,"enti_p":0,"enti_t":5,"perc":"0","vot_m":0,"vot_f":0,"vot_t":0,"perc_r":"0"},{"com":3,"dt_com":20251123230000,"enti_p":0,"enti_t":5,"perc":"0","vot_m":0,"vot_f":0,"vot_t":0,"perc_r":"0"},{"com":4,"dt_com":20251124150000,"enti_p":0,"enti_t":5,"perc":"0","vot_m":0,"vot_f":0,"vot_t":0,"perc_r":"0"}]},{"tipo":"COMUNE","desc":"NOCIGLIA","cod":530,"ele_m":0,"ele_f":0,"ele_t":2131,"una_lis":null,"tipo_tras":"SZ","com_vot":[{"com":1,"dt_com":20251123120000,"enti_p":0,"enti_t":3,"perc":"0","vot_m":0,"vot_f":0,"vot_t":0,"perc_r":"0"},{"com":2,"dt_com":20251123190000,"enti_p":0,"enti_t":3,"perc":"0","vot_m":0,"vot_f":0,"vot_t":0,"perc_r":"0"},{"com":3,"dt_com":20251123230000,"enti_p":0,"enti_t":3,"perc":"0","vot_m":0,"vot_f":0,"vot_t":0,"perc_r":"0"},{"com":4,"dt_com":20251124150000,"enti_p":0,"enti_t":3,"perc":"0","vot_m":0,"vot_f":0,"vot_t":0,"perc_r":"0"}]},{"tipo":"COMUNE","desc":"NOVOLI","cod":540,"ele_m":0,"ele_f":0,"ele_t":6900,"una_lis":null,"tipo_tras":"SZ","com_vot":[{"com":1,"dt_com":20251123120000,"enti_p":0,"enti_t":7,"perc":"0","vot_m":0,"vot_f":0,"vot_t":0,"perc_r":"0"},{"com":2,"dt_com":20251123190000,"enti_p":0,"enti_t":7,"perc":"0","vot_m":0,"vot_f":0,"vot_t":0,"perc_r":"0"},{"com":3,"dt_com":20251123230000,"enti_p":0,"enti_t":7,"perc":"0","vot_m":0,"vot_f":0,"vot_t":0,"perc_r":"0"},{"com":4,"dt_com":20251124150000,"enti_p":0,"enti_t":7,"perc":"0","vot_m":0,"vot_f":0,"vot_t":0,"perc_r":"0"}]},{"tipo":"COMUNE","desc":"ORTELLE","cod":550,"ele_m":0,"ele_f":0,"ele_t":2118,"una_lis":null,"tipo_tras":"SZ","com_vot":[{"com":1,"dt_com":20251123120000,"enti_p":0,"enti_t":3,"perc":"0","vot_m":0,"vot_f":0,"vot_t":0,"perc_r":"0"},{"com":2,"dt_com":20251123190000,"enti_p":0,"enti_t":3,"perc":"0","vot_m":0,"vot_f":0,"vot_t":0,"perc_r":"0"},{"com":3,"dt_com":20251123230000,"enti_p":0,"enti_t":3,"perc":"0","vot_m":0,"vot_f":0,"vot_t":0,"perc_r":"0"},{"com":4,"dt_com":20251124150000,"enti_p":0,"enti_t":3,"perc":"0","vot_m":0,"vot_f":0,"vot_t":0,"perc_r":"0"}]},{"tipo":"COMUNE","desc":"OTRANTO","cod":560,"ele_m":0,"ele_f":0,"ele_t":5203,"una_lis":null,"tipo_tras":"SZ","com_vot":[{"com":1,"dt_com":20251123120000,"enti_p":0,"enti_t":6,"perc":"0","vot_m":0,"vot_f":0,"vot_t":0,"perc_r":"0"},{"com":2,"dt_com":20251123190000,"enti_p":0,"enti_t":6,"perc":"0","vot_m":0,"vot_f":0,"vot_t":0,"perc_r":"0"},{"com":3,"dt_com":20251123230000,"enti_p":0,"enti_t":6,"perc":"0","vot_m":0,"vot_f":0,"vot_t":0,"perc_r":"0"},{"com":4,"dt_com":20251124150000,"enti_p":0,"enti_t":6,"perc":"0","vot_m":0,"vot_f":0,"vot_t":0,"perc_r":"0"}]},{"tipo":"COMUNE","desc":"PALMARIGGI","cod":570,"ele_m":0,"ele_f":0,"ele_t":1407,"una_lis":null,"tipo_tras":"SZ","com_vot":[{"com":1,"dt_com":20251123120000,"enti_p":0,"enti_t":2,"perc":"0","vot_m":0,"vot_f":0,"vot_t":0,"perc_r":"0"},{"com":2,"dt_com":20251123190000,"enti_p":0,"enti_t":2,"perc":"0","vot_m":0,"vot_f":0,"vot_t":0,"perc_r":"0"},{"com":3,"dt_com":20251123230000,"enti_p":0,"enti_t":2,"perc":"0","vot_m":0,"vot_f":0,"vot_t":0,"perc_r":"0"},{"com":4,"dt_com":20251124150000,"enti_p":0,"enti_t":2,"perc":"0","vot_m":0,"vot_f":0,"vot_t":0,"perc_r":"0"}]},{"tipo":"COMUNE","desc":"PARABITA","cod":580,"ele_m":0,"ele_f":0,"ele_t":9016,"una_lis":null,"tipo_tras":"SZ","com_vot":[{"com":1,"dt_com":20251123120000,"enti_p":0,"enti_t":10,"perc":"0","vot_m":0,"vot_f":0,"vot_t":0,"perc_r":"0"},{"com":2,"dt_com":20251123190000,"enti_p":0,"enti_t":10,"perc":"0","vot_m":0,"vot_f":0,"vot_t":0,"perc_r":"0"},{"com":3,"dt_com":20251123230000,"enti_p":0,"enti_t":10,"perc":"0","vot_m":0,"vot_f":0,"vot_t":0,"perc_r":"0"},{"com":4,"dt_com":20251124150000,"enti_p":0,"enti_t":10,"perc":"0","vot_m":0,"vot_f":0,"vot_t":0,"perc_r":"0"}]},{"tipo":"COMUNE","desc":"PATU'","cod":590,"ele_m":0,"ele_f":0,"ele_t":1750,"una_lis":null,"tipo_tras":"SZ","com_vot":[{"com":1,"dt_com":20251123120000,"enti_p":0,"enti_t":2,"perc":"0","vot_m":0,"vot_f":0,"vot_t":0,"perc_r":"0"},{"com":2,"dt_com":20251123190000,"enti_p":0,"enti_t":2,"perc":"0","vot_m":0,"vot_f":0,"vot_t":0,"perc_r":"0"},{"com":3,"dt_com":20251123230000,"enti_p":0,"enti_t":2,"perc":"0","vot_m":0,"vot_f":0,"vot_t":0,"perc_r":"0"},{"com":4,"dt_com":20251124150000,"enti_p":0,"enti_t":2,"perc":"0","vot_m":0,"vot_f":0,"vot_t":0,"perc_r":"0"}]},{"tipo":"COMUNE","desc":"POGGIARDO","cod":600,"ele_m":0,"ele_f":0,"ele_t":5258,"una_lis":null,"tipo_tras":"SZ","com_vot":[{"com":1,"dt_com":20251123120000,"enti_p":0,"enti_t":6,"perc":"0","vot_m":0,"vot_f":0,"vot_t":0,"perc_r":"0"},{"com":2,"dt_com":20251123190000,"enti_p":0,"enti_t":6,"perc":"0","vot_m":0,"vot_f":0,"vot_t":0,"perc_r":"0"},{"com":3,"dt_com":20251123230000,"enti_p":0,"enti_t":6,"perc":"0","vot_m":0,"vot_f":0,"vot_t":0,"perc_r":"0"},{"com":4,"dt_com":20251124150000,"enti_p":0,"enti_t":6,"perc":"0","vot_m":0,"vot_f":0,"vot_t":0,"perc_r":"0"}]},{"tipo":"COMUNE","desc":"PORTO CESAREO","cod":601,"ele_m":0,"ele_f":0,"ele_t":5864,"una_lis":null,"tipo_tras":"SZ","com_vot":[{"com":1,"dt_com":20251123120000,"enti_p":0,"enti_t":6,"perc":"0","vot_m":0,"vot_f":0,"vot_t":0,"perc_r":"0"},{"com":2,"dt_com":20251123190000,"enti_p":0,"enti_t":6,"perc":"0","vot_m":0,"vot_f":0,"vot_t":0,"perc_r":"0"},{"com":3,"dt_com":20251123230000,"enti_p":0,"enti_t":6,"perc":"0","vot_m":0,"vot_f":0,"vot_t":0,"perc_r":"0"},{"com":4,"dt_com":20251124150000,"enti_p":0,"enti_t":6,"perc":"0","vot_m":0,"vot_f":0,"vot_t":0,"perc_r":"0"}]},{"tipo":"COMUNE","desc":"PRESICCE-ACQUARICA","cod":611,"ele_m":0,"ele_f":0,"ele_t":10887,"una_lis":null,"tipo_tras":"SZ","com_vot":[{"com":1,"dt_com":20251123120000,"enti_p":0,"enti_t":12,"perc":"0","vot_m":0,"vot_f":0,"vot_t":0,"perc_r":"0"},{"com":2,"dt_com":20251123190000,"enti_p":0,"enti_t":12,"perc":"0","vot_m":0,"vot_f":0,"vot_t":0,"perc_r":"0"},{"com":3,"dt_com":20251123230000,"enti_p":0,"enti_t":12,"perc":"0","vot_m":0,"vot_f":0,"vot_t":0,"perc_r":"0"},{"com":4,"dt_com":20251124150000,"enti_p":0,"enti_t":12,"perc":"0","vot_m":0,"vot_f":0,"vot_t":0,"perc_r":"0"}]},{"tipo":"COMUNE","desc":"RACALE","cod":620,"ele_m":0,"ele_f":0,"ele_t":10071,"una_lis":null,"tipo_tras":"SZ","com_vot":[{"com":1,"dt_com":20251123120000,"enti_p":0,"enti_t":11,"perc":"0","vot_m":0,"vot_f":0,"vot_t":0,"perc_r":"0"},{"com":2,"dt_com":20251123190000,"enti_p":0,"enti_t":11,"perc":"0","vot_m":0,"vot_f":0,"vot_t":0,"perc_r":"0"},{"com":3,"dt_com":20251123230000,"enti_p":0,"enti_t":11,"perc":"0","vot_m":0,"vot_f":0,"vot_t":0,"perc_r":"0"},{"com":4,"dt_com":20251124150000,"enti_p":0,"enti_t":11,"perc":"0","vot_m":0,"vot_f":0,"vot_t":0,"perc_r":"0"}]},{"tipo":"COMUNE","desc":"RUFFANO","cod":630,"ele_m":0,"ele_f":0,"ele_t":9236,"una_lis":null,"tipo_tras":"SZ","com_vot":[{"com":1,"dt_com":20251123120000,"enti_p":0,"enti_t":10,"perc":"0","vot_m":0,"vot_f":0,"vot_t":0,"perc_r":"0"},{"com":2,"dt_com":20251123190000,"enti_p":0,"enti_t":10,"perc":"0","vot_m":0,"vot_f":0,"vot_t":0,"perc_r":"0"},{"com":3,"dt_com":20251123230000,"enti_p":0,"enti_t":10,"perc":"0","vot_m":0,"vot_f":0,"vot_t":0,"perc_r":"0"},{"com":4,"dt_com":20251124150000,"enti_p":0,"enti_t":10,"perc":"0","vot_m":0,"vot_f":0,"vot_t":0,"perc_r":"0"}]},{"tipo":"COMUNE","desc":"SALICE SALENTINO","cod":640,"ele_m":0,"ele_f":0,"ele_t":7308,"una_lis":null,"tipo_tras":"SZ","com_vot":[{"com":1,"dt_com":20251123120000,"enti_p":0,"enti_t":7,"perc":"0","vot_m":0,"vot_f":0,"vot_t":0,"perc_r":"0"},{"com":2,"dt_com":20251123190000,"enti_p":0,"enti_t":7,"perc":"0","vot_m":0,"vot_f":0,"vot_t":0,"perc_r":"0"},{"com":3,"dt_com":20251123230000,"enti_p":0,"enti_t":7,"perc":"0","vot_m":0,"vot_f":0,"vot_t":0,"perc_r":"0"},{"com":4,"dt_com":20251124150000,"enti_p":0,"enti_t":7,"perc":"0","vot_m":0,"vot_f":0,"vot_t":0,"perc_r":"0"}]},{"tipo":"COMUNE","desc":"SALVE","cod":650,"ele_m":0,"ele_f":0,"ele_t":5690,"una_lis":null,"tipo_tras":"SZ","com_vot":[{"com":1,"dt_com":20251123120000,"enti_p":0,"enti_t":5,"perc":"0","vot_m":0,"vot_f":0,"vot_t":0,"perc_r":"0"},{"com":2,"dt_com":20251123190000,"enti_p":0,"enti_t":5,"perc":"0","vot_m":0,"vot_f":0,"vot_t":0,"perc_r":"0"},{"com":3,"dt_com":20251123230000,"enti_p":0,"enti_t":5,"perc":"0","vot_m":0,"vot_f":0,"vot_t":0,"perc_r":"0"},{"com":4,"dt_com":20251124150000,"enti_p":0,"enti_t":5,"perc":"0","vot_m":0,"vot_f":0,"vot_t":0,"perc_r":"0"}]},{"tipo":"COMUNE","desc":"SAN CASSIANO","cod":661,"ele_m":0,"ele_f":0,"ele_t":1784,"una_lis":null,"tipo_tras":"SZ","com_vot":[{"com":1,"dt_com":20251123120000,"enti_p":0,"enti_t":2,"perc":"0","vot_m":0,"vot_f":0,"vot_t":0,"perc_r":"0"},{"com":2,"dt_com":20251123190000,"enti_p":0,"enti_t":2,"perc":"0","vot_m":0,"vot_f":0,"vot_t":0,"perc_r":"0"},{"com":3,"dt_com":20251123230000,"enti_p":0,"enti_t":2,"perc":"0","vot_m":0,"vot_f":0,"vot_t":0,"perc_r":"0"},{"com":4,"dt_com":20251124150000,"enti_p":0,"enti_t":2,"perc":"0","vot_m":0,"vot_f":0,"vot_t":0,"perc_r":"0"}]},{"tipo":"COMUNE","desc":"SAN CESARIO DI LECCE","cod":670,"ele_m":0,"ele_f":0,"ele_t":6703,"una_lis":null,"tipo_tras":"SZ","com_vot":[{"com":1,"dt_com":20251123120000,"enti_p":0,"enti_t":7,"perc":"0","vot_m":0,"vot_f":0,"vot_t":0,"perc_r":"0"},{"com":2,"dt_com":20251123190000,"enti_p":0,"enti_t":7,"perc":"0","vot_m":0,"vot_f":0,"vot_t":0,"perc_r":"0"},{"com":3,"dt_com":20251123230000,"enti_p":0,"enti_t":7,"perc":"0","vot_m":0,"vot_f":0,"vot_t":0,"perc_r":"0"},{"com":4,"dt_com":20251124150000,"enti_p":0,"enti_t":7,"perc":"0","vot_m":0,"vot_f":0,"vot_t":0,"perc_r":"0"}]},{"tipo":"COMUNE","desc":"SAN DONATO DI LECCE","cod":680,"ele_m":0,"ele_f":0,"ele_t":4765,"una_lis":null,"tipo_tras":"SZ","com_vot":[{"com":1,"dt_com":20251123120000,"enti_p":0,"enti_t":5,"perc":"0","vot_m":0,"vot_f":0,"vot_t":0,"perc_r":"0"},{"com":2,"dt_com":20251123190000,"enti_p":0,"enti_t":5,"perc":"0","vot_m":0,"vot_f":0,"vot_t":0,"perc_r":"0"},{"com":3,"dt_com":20251123230000,"enti_p":0,"enti_t":5,"perc":"0","vot_m":0,"vot_f":0,"vot_t":0,"perc_r":"0"},{"com":4,"dt_com":20251124150000,"enti_p":0,"enti_t":5,"perc":"0","vot_m":0,"vot_f":0,"vot_t":0,"perc_r":"0"}]},{"tipo":"COMUNE","desc":"SAN PIETRO IN LAMA","cod":700,"ele_m":0,"ele_f":0,"ele_t":3018,"una_lis":null,"tipo_tras":"SZ","com_vot":[{"com":1,"dt_com":20251123120000,"enti_p":0,"enti_t":4,"perc":"0","vot_m":0,"vot_f":0,"vot_t":0,"perc_r":"0"},{"com":2,"dt_com":20251123190000,"enti_p":0,"enti_t":4,"perc":"0","vot_m":0,"vot_f":0,"vot_t":0,"perc_r":"0"},{"com":3,"dt_com":20251123230000,"enti_p":0,"enti_t":4,"perc":"0","vot_m":0,"vot_f":0,"vot_t":0,"perc_r":"0"},{"com":4,"dt_com":20251124150000,"enti_p":0,"enti_t":4,"perc":"0","vot_m":0,"vot_f":0,"vot_t":0,"perc_r":"0"}]},{"tipo":"COMUNE","desc":"SANARICA","cod":660,"ele_m":0,"ele_f":0,"ele_t":1453,"una_lis":null,"tipo_tras":"SZ","com_vot":[{"com":1,"dt_com":20251123120000,"enti_p":0,"enti_t":2,"perc":"0","vot_m":0,"vot_f":0,"vot_t":0,"perc_r":"0"},{"com":2,"dt_com":20251123190000,"enti_p":0,"enti_t":2,"perc":"0","vot_m":0,"vot_f":0,"vot_t":0,"perc_r":"0"},{"com":3,"dt_com":20251123230000,"enti_p":0,"enti_t":2,"perc":"0","vot_m":0,"vot_f":0,"vot_t":0,"perc_r":"0"},{"com":4,"dt_com":20251124150000,"enti_p":0,"enti_t":2,"perc":"0","vot_m":0,"vot_f":0,"vot_t":0,"perc_r":"0"}]},{"tipo":"COMUNE","desc":"SANNICOLA","cod":690,"ele_m":0,"ele_f":0,"ele_t":5961,"una_lis":null,"tipo_tras":"SZ","com_vot":[{"com":1,"dt_com":20251123120000,"enti_p":0,"enti_t":7,"perc":"0","vot_m":0,"vot_f":0,"vot_t":0,"perc_r":"0"},{"com":2,"dt_com":20251123190000,"enti_p":0,"enti_t":7,"perc":"0","vot_m":0,"vot_f":0,"vot_t":0,"perc_r":"0"},{"com":3,"dt_com":20251123230000,"enti_p":0,"enti_t":7,"perc":"0","vot_m":0,"vot_f":0,"vot_t":0,"perc_r":"0"},{"com":4,"dt_com":20251124150000,"enti_p":0,"enti_t":7,"perc":"0","vot_m":0,"vot_f":0,"vot_t":0,"perc_r":"0"}]},{"tipo":"COMUNE","desc":"SANTA CESAREA TERME","cod":710,"ele_m":0,"ele_f":0,"ele_t":2537,"una_lis":null,"tipo_tras":"SZ","com_vot":[{"com":1,"dt_com":20251123120000,"enti_p":0,"enti_t":4,"perc":"0","vot_m":0,"vot_f":0,"vot_t":0,"perc_r":"0"},{"com":2,"dt_com":20251123190000,"enti_p":0,"enti_t":4,"perc":"0","vot_m":0,"vot_f":0,"vot_t":0,"perc_r":"0"},{"com":3,"dt_com":20251123230000,"enti_p":0,"enti_t":4,"perc":"0","vot_m":0,"vot_f":0,"vot_t":0,"perc_r":"0"},{"com":4,"dt_com":20251124150000,"enti_p":0,"enti_t":4,"perc":"0","vot_m":0,"vot_f":0,"vot_t":0,"perc_r":"0"}]},{"tipo":"COMUNE","desc":"SCORRANO","cod":720,"ele_m":0,"ele_f":0,"ele_t":6691,"una_lis":null,"tipo_tras":"SZ","com_vot":[{"com":1,"dt_com":20251123120000,"enti_p":0,"enti_t":8,"perc":"0","vot_m":0,"vot_f":0,"vot_t":0,"perc_r":"0"},{"com":2,"dt_com":20251123190000,"enti_p":0,"enti_t":8,"perc":"0","vot_m":0,"vot_f":0,"vot_t":0,"perc_r":"0"},{"com":3,"dt_com":20251123230000,"enti_p":0,"enti_t":8,"perc":"0","vot_m":0,"vot_f":0,"vot_t":0,"perc_r":"0"},{"com":4,"dt_com":20251124150000,"enti_p":0,"enti_t":8,"perc":"0","vot_m":0,"vot_f":0,"vot_t":0,"perc_r":"0"}]},{"tipo":"COMUNE","desc":"SECLI'","cod":730,"ele_m":0,"ele_f":0,"ele_t":1837,"una_lis":null,"tipo_tras":"SZ","com_vot":[{"com":1,"dt_com":20251123120000,"enti_p":0,"enti_t":2,"perc":"0","vot_m":0,"vot_f":0,"vot_t":0,"perc_r":"0"},{"com":2,"dt_com":20251123190000,"enti_p":0,"enti_t":2,"perc":"0","vot_m":0,"vot_f":0,"vot_t":0,"perc_r":"0"},{"com":3,"dt_com":20251123230000,"enti_p":0,"enti_t":2,"perc":"0","vot_m":0,"vot_f":0,"vot_t":0,"perc_r":"0"},{"com":4,"dt_com":20251124150000,"enti_p":0,"enti_t":2,"perc":"0","vot_m":0,"vot_f":0,"vot_t":0,"perc_r":"0"}]},{"tipo":"COMUNE","desc":"SOGLIANO CAVOUR","cod":740,"ele_m":0,"ele_f":0,"ele_t":3617,"una_lis":null,"tipo_tras":"SZ","com_vot":[{"com":1,"dt_com":20251123120000,"enti_p":0,"enti_t":4,"perc":"0","vot_m":0,"vot_f":0,"vot_t":0,"perc_r":"0"},{"com":2,"dt_com":20251123190000,"enti_p":0,"enti_t":4,"perc":"0","vot_m":0,"vot_f":0,"vot_t":0,"perc_r":"0"},{"com":3,"dt_com":20251123230000,"enti_p":0,"enti_t":4,"perc":"0","vot_m":0,"vot_f":0,"vot_t":0,"perc_r":"0"},{"com":4,"dt_com":20251124150000,"enti_p":0,"enti_t":4,"perc":"0","vot_m":0,"vot_f":0,"vot_t":0,"perc_r":"0"}]},{"tipo":"COMUNE","desc":"SOLETO","cod":750,"ele_m":0,"ele_f":0,"ele_t":4605,"una_lis":null,"tipo_tras":"SZ","com_vot":[{"com":1,"dt_com":20251123120000,"enti_p":0,"enti_t":5,"perc":"0","vot_m":0,"vot_f":0,"vot_t":0,"perc_r":"0"},{"com":2,"dt_com":20251123190000,"enti_p":0,"enti_t":5,"perc":"0","vot_m":0,"vot_f":0,"vot_t":0,"perc_r":"0"},{"com":3,"dt_com":20251123230000,"enti_p":0,"enti_t":5,"perc":"0","vot_m":0,"vot_f":0,"vot_t":0,"perc_r":"0"},{"com":4,"dt_com":20251124150000,"enti_p":0,"enti_t":5,"perc":"0","vot_m":0,"vot_f":0,"vot_t":0,"perc_r":"0"}]},{"tipo":"COMUNE","desc":"SPECCHIA","cod":760,"ele_m":0,"ele_f":0,"ele_t":4696,"una_lis":null,"tipo_tras":"SZ","com_vot":[{"com":1,"dt_com":20251123120000,"enti_p":0,"enti_t":5,"perc":"0","vot_m":0,"vot_f":0,"vot_t":0,"perc_r":"0"},{"com":2,"dt_com":20251123190000,"enti_p":0,"enti_t":5,"perc":"0","vot_m":0,"vot_f":0,"vot_t":0,"perc_r":"0"},{"com":3,"dt_com":20251123230000,"enti_p":0,"enti_t":5,"perc":"0","vot_m":0,"vot_f":0,"vot_t":0,"perc_r":"0"},{"com":4,"dt_com":20251124150000,"enti_p":0,"enti_t":5,"perc":"0","vot_m":0,"vot_f":0,"vot_t":0,"perc_r":"0"}]},{"tipo":"COMUNE","desc":"SPONGANO","cod":770,"ele_m":0,"ele_f":0,"ele_t":3266,"una_lis":null,"tipo_tras":"SZ","com_vot":[{"com":1,"dt_com":20251123120000,"enti_p":0,"enti_t":4,"perc":"0","vot_m":0,"vot_f":0,"vot_t":0,"perc_r":"0"},{"com":2,"dt_com":20251123190000,"enti_p":0,"enti_t":4,"perc":"0","vot_m":0,"vot_f":0,"vot_t":0,"perc_r":"0"},{"com":3,"dt_com":20251123230000,"enti_p":0,"enti_t":4,"perc":"0","vot_m":0,"vot_f":0,"vot_t":0,"perc_r":"0"},{"com":4,"dt_com":20251124150000,"enti_p":0,"enti_t":4,"perc":"0","vot_m":0,"vot_f":0,"vot_t":0,"perc_r":"0"}]},{"tipo":"COMUNE","desc":"SQUINZANO","cod":780,"ele_m":0,"ele_f":0,"ele_t":12776,"una_lis":null,"tipo_tras":"SZ","com_vot":[{"com":1,"dt_com":20251123120000,"enti_p":0,"enti_t":18,"perc":"0","vot_m":0,"vot_f":0,"vot_t":0,"perc_r":"0"},{"com":2,"dt_com":20251123190000,"enti_p":0,"enti_t":18,"perc":"0","vot_m":0,"vot_f":0,"vot_t":0,"perc_r":"0"},{"com":3,"dt_com":20251123230000,"enti_p":0,"enti_t":18,"perc":"0","vot_m":0,"vot_f":0,"vot_t":0,"perc_r":"0"},{"com":4,"dt_com":20251124150000,"enti_p":0,"enti_t":18,"perc":"0","vot_m":0,"vot_f":0,"vot_t":0,"perc_r":"0"}]},{"tipo":"COMUNE","desc":"STERNATIA","cod":790,"ele_m":0,"ele_f":0,"ele_t":1889,"una_lis":null,"tipo_tras":"SZ","com_vot":[{"com":1,"dt_com":20251123120000,"enti_p":0,"enti_t":3,"perc":"0","vot_m":0,"vot_f":0,"vot_t":0,"perc_r":"0"},{"com":2,"dt_com":20251123190000,"enti_p":0,"enti_t":3,"perc":"0","vot_m":0,"vot_f":0,"vot_t":0,"perc_r":"0"},{"com":3,"dt_com":20251123230000,"enti_p":0,"enti_t":3,"perc":"0","vot_m":0,"vot_f":0,"vot_t":0,"perc_r":"0"},{"com":4,"dt_com":20251124150000,"enti_p":0,"enti_t":3,"perc":"0","vot_m":0,"vot_f":0,"vot_t":0,"perc_r":"0"}]},{"tipo":"COMUNE","desc":"SUPERSANO","cod":800,"ele_m":0,"ele_f":0,"ele_t":4053,"una_lis":null,"tipo_tras":"SZ","com_vot":[{"com":1,"dt_com":20251123120000,"enti_p":0,"enti_t":4,"perc":"0","vot_m":0,"vot_f":0,"vot_t":0,"perc_r":"0"},{"com":2,"dt_com":20251123190000,"enti_p":0,"enti_t":4,"perc":"0","vot_m":0,"vot_f":0,"vot_t":0,"perc_r":"0"},{"com":3,"dt_com":20251123230000,"enti_p":0,"enti_t":4,"perc":"0","vot_m":0,"vot_f":0,"vot_t":0,"perc_r":"0"},{"com":4,"dt_com":20251124150000,"enti_p":0,"enti_t":4,"perc":"0","vot_m":0,"vot_f":0,"vot_t":0,"perc_r":"0"}]},{"tipo":"COMUNE","desc":"SURANO","cod":810,"ele_m":0,"ele_f":0,"ele_t":1574,"una_lis":null,"tipo_tras":"SZ","com_vot":[{"com":1,"dt_com":20251123120000,"enti_p":0,"enti_t":2,"perc":"0","vot_m":0,"vot_f":0,"vot_t":0,"perc_r":"0"},{"com":2,"dt_com":20251123190000,"enti_p":0,"enti_t":2,"perc":"0","vot_m":0,"vot_f":0,"vot_t":0,"perc_r":"0"},{"com":3,"dt_com":20251123230000,"enti_p":0,"enti_t":2,"perc":"0","vot_m":0,"vot_f":0,"vot_t":0,"perc_r":"0"},{"com":4,"dt_com":20251124150000,"enti_p":0,"enti_t":2,"perc":"0","vot_m":0,"vot_f":0,"vot_t":0,"perc_r":"0"}]},{"tipo":"COMUNE","desc":"SURBO","cod":820,"ele_m":0,"ele_f":0,"ele_t":12316,"una_lis":null,"tipo_tras":"SZ","com_vot":[{"com":1,"dt_com":20251123120000,"enti_p":0,"enti_t":13,"perc":"0","vot_m":0,"vot_f":0,"vot_t":0,"perc_r":"0"},{"com":2,"dt_com":20251123190000,"enti_p":0,"enti_t":13,"perc":"0","vot_m":0,"vot_f":0,"vot_t":0,"perc_r":"0"},{"com":3,"dt_com":20251123230000,"enti_p":0,"enti_t":13,"perc":"0","vot_m":0,"vot_f":0,"vot_t":0,"perc_r":"0"},{"com":4,"dt_com":20251124150000,"enti_p":0,"enti_t":13,"perc":"0","vot_m":0,"vot_f":0,"vot_t":0,"perc_r":"0"}]},{"tipo":"COMUNE","desc":"TAURISANO","cod":830,"ele_m":0,"ele_f":0,"ele_t":12476,"una_lis":null,"tipo_tras":"SZ","com_vot":[{"com":1,"dt_com":20251123120000,"enti_p":0,"enti_t":14,"perc":"0","vot_m":0,"vot_f":0,"vot_t":0,"perc_r":"0"},{"com":2,"dt_com":20251123190000,"enti_p":0,"enti_t":14,"perc":"0","vot_m":0,"vot_f":0,"vot_t":0,"perc_r":"0"},{"com":3,"dt_com":20251123230000,"enti_p":0,"enti_t":14,"perc":"0","vot_m":0,"vot_f":0,"vot_t":0,"perc_r":"0"},{"com":4,"dt_com":20251124150000,"enti_p":0,"enti_t":14,"perc":"0","vot_m":0,"vot_f":0,"vot_t":0,"perc_r":"0"}]},{"tipo":"COMUNE","desc":"TAVIANO","cod":840,"ele_m":0,"ele_f":0,"ele_t":10466,"una_lis":null,"tipo_tras":"SZ","com_vot":[{"com":1,"dt_com":20251123120000,"enti_p":0,"enti_t":11,"perc":"0","vot_m":0,"vot_f":0,"vot_t":0,"perc_r":"0"},{"com":2,"dt_com":20251123190000,"enti_p":0,"enti_t":11,"perc":"0","vot_m":0,"vot_f":0,"vot_t":0,"perc_r":"0"},{"com":3,"dt_com":20251123230000,"enti_p":0,"enti_t":11,"perc":"0","vot_m":0,"vot_f":0,"vot_t":0,"perc_r":"0"},{"com":4,"dt_com":20251124150000,"enti_p":0,"enti_t":11,"perc":"0","vot_m":0,"vot_f":0,"vot_t":0,"perc_r":"0"}]},{"tipo":"COMUNE","desc":"TIGGIANO","cod":850,"ele_m":0,"ele_f":0,"ele_t":2595,"una_lis":null,"tipo_tras":"SZ","com_vot":[{"com":1,"dt_com":20251123120000,"enti_p":0,"enti_t":3,"perc":"0","vot_m":0,"vot_f":0,"vot_t":0,"perc_r":"0"},{"com":2,"dt_com":20251123190000,"enti_p":0,"enti_t":3,"perc":"0","vot_m":0,"vot_f":0,"vot_t":0,"perc_r":"0"},{"com":3,"dt_com":20251123230000,"enti_p":0,"enti_t":3,"perc":"0","vot_m":0,"vot_f":0,"vot_t":0,"perc_r":"0"},{"com":4,"dt_com":20251124150000,"enti_p":0,"enti_t":3,"perc":"0","vot_m":0,"vot_f":0,"vot_t":0,"perc_r":"0"}]},{"tipo":"COMUNE","desc":"TREPUZZI","cod":860,"ele_m":0,"ele_f":0,"ele_t":12192,"una_lis":null,"tipo_tras":"SZ","com_vot":[{"com":1,"dt_com":20251123120000,"enti_p":0,"enti_t":13,"perc":"0","vot_m":0,"vot_f":0,"vot_t":0,"perc_r":"0"},{"com":2,"dt_com":20251123190000,"enti_p":0,"enti_t":13,"perc":"0","vot_m":0,"vot_f":0,"vot_t":0,"perc_r":"0"},{"com":3,"dt_com":20251123230000,"enti_p":0,"enti_t":13,"perc":"0","vot_m":0,"vot_f":0,"vot_t":0,"perc_r":"0"},{"com":4,"dt_com":20251124150000,"enti_p":0,"enti_t":13,"perc":"0","vot_m":0,"vot_f":0,"vot_t":0,"perc_r":"0"}]},{"tipo":"COMUNE","desc":"TRICASE","cod":870,"ele_m":0,"ele_f":0,"ele_t":15868,"una_lis":null,"tipo_tras":"SZ","com_vot":[{"com":1,"dt_com":20251123120000,"enti_p":0,"enti_t":21,"perc":"0","vot_m":0,"vot_f":0,"vot_t":0,"perc_r":"0"},{"com":2,"dt_com":20251123190000,"enti_p":0,"enti_t":21,"perc":"0","vot_m":0,"vot_f":0,"vot_t":0,"perc_r":"0"},{"com":3,"dt_com":20251123230000,"enti_p":0,"enti_t":21,"perc":"0","vot_m":0,"vot_f":0,"vot_t":0,"perc_r":"0"},{"com":4,"dt_com":20251124150000,"enti_p":0,"enti_t":21,"perc":"0","vot_m":0,"vot_f":0,"vot_t":0,"perc_r":"0"}]},{"tipo":"COMUNE","desc":"TUGLIE","cod":880,"ele_m":0,"ele_f":0,"ele_t":5938,"una_lis":null,"tipo_tras":"SZ","com_vot":[{"com":1,"dt_com":20251123120000,"enti_p":0,"enti_t":6,"perc":"0","vot_m":0,"vot_f":0,"vot_t":0,"perc_r":"0"},{"com":2,"dt_com":20251123190000,"enti_p":0,"enti_t":6,"perc":"0","vot_m":0,"vot_f":0,"vot_t":0,"perc_r":"0"},{"com":3,"dt_com":20251123230000,"enti_p":0,"enti_t":6,"perc":"0","vot_m":0,"vot_f":0,"vot_t":0,"perc_r":"0"},{"com":4,"dt_com":20251124150000,"enti_p":0,"enti_t":6,"perc":"0","vot_m":0,"vot_f":0,"vot_t":0,"perc_r":"0"}]},{"tipo":"COMUNE","desc":"UGENTO","cod":890,"ele_m":0,"ele_f":0,"ele_t":13020,"una_lis":null,"tipo_tras":"SZ","com_vot":[{"com":1,"dt_com":20251123120000,"enti_p":0,"enti_t":14,"perc":"0","vot_m":0,"vot_f":0,"vot_t":0,"perc_r":"0"},{"com":2,"dt_com":20251123190000,"enti_p":0,"enti_t":14,"perc":"0","vot_m":0,"vot_f":0,"vot_t":0,"perc_r":"0"},{"com":3,"dt_com":20251123230000,"enti_p":0,"enti_t":14,"perc":"0","vot_m":0,"vot_f":0,"vot_t":0,"perc_r":"0"},{"com":4,"dt_com":20251124150000,"enti_p":0,"enti_t":14,"perc":"0","vot_m":0,"vot_f":0,"vot_t":0,"perc_r":"0"}]},{"tipo":"COMUNE","desc":"UGGIANO LA CHIESA","cod":900,"ele_m":0,"ele_f":0,"ele_t":4121,"una_lis":null,"tipo_tras":"SZ","com_vot":[{"com":1,"dt_com":20251123120000,"enti_p":0,"enti_t":4,"perc":"0","vot_m":0,"vot_f":0,"vot_t":0,"perc_r":"0"},{"com":2,"dt_com":20251123190000,"enti_p":0,"enti_t":4,"perc":"0","vot_m":0,"vot_f":0,"vot_t":0,"perc_r":"0"},{"com":3,"dt_com":20251123230000,"enti_p":0,"enti_t":4,"perc":"0","vot_m":0,"vot_f":0,"vot_t":0,"perc_r":"0"},{"com":4,"dt_com":20251124150000,"enti_p":0,"enti_t":4,"perc":"0","vot_m":0,"vot_f":0,"vot_t":0,"perc_r":"0"}]},{"tipo":"COMUNE","desc":"VEGLIE","cod":910,"ele_m":0,"ele_f":0,"ele_t":11988,"una_lis":null,"tipo_tras":"SZ","com_vot":[{"com":1,"dt_com":20251123120000,"enti_p":0,"enti_t":12,"perc":"0","vot_m":0,"vot_f":0,"vot_t":0,"perc_r":"0"},{"com":2,"dt_com":20251123190000,"enti_p":0,"enti_t":12,"perc":"0","vot_m":0,"vot_f":0,"vot_t":0,"perc_r":"0"},{"com":3,"dt_com":20251123230000,"enti_p":0,"enti_t":12,"perc":"0","vot_m":0,"vot_f":0,"vot_t":0,"perc_r":"0"},{"com":4,"dt_com":20251124150000,"enti_p":0,"enti_t":12,"perc":"0","vot_m":0,"vot_f":0,"vot_t":0,"perc_r":"0"}]},{"tipo":"COMUNE","desc":"VERNOLE","cod":920,"ele_m":0,"ele_f":0,"ele_t":6032,"una_lis":null,"tipo_tras":"SZ","com_vot":[{"com":1,"dt_com":20251123120000,"enti_p":0,"enti_t":9,"perc":"0","vot_m":0,"vot_f":0,"vot_t":0,"perc_r":"0"},{"com":2,"dt_com":20251123190000,"enti_p":0,"enti_t":9,"perc":"0","vot_m":0,"vot_f":0,"vot_t":0,"perc_r":"0"},{"com":3,"dt_com":20251123230000,"enti_p":0,"enti_t":9,"perc":"0","vot_m":0,"vot_f":0,"vot_t":0,"perc_r":"0"},{"com":4,"dt_com":20251124150000,"enti_p":0,"enti_t":9,"perc":"0","vot_m":0,"vot_f":0,"vot_t":0,"perc_r":"0"}]},{"tipo":"COMUNE","desc":"ZOLLINO","cod":930,"ele_m":0,"ele_f":0,"ele_t":1872,"una_lis":null,"tipo_tras":"SZ","com_vot":[{"com":1,"dt_com":20251123120000,"enti_p":0,"enti_t":2,"perc":"0","vot_m":0,"vot_f":0,"vot_t":0,"perc_r":"0"},{"com":2,"dt_com":20251123190000,"enti_p":0,"enti_t":2,"perc":"0","vot_m":0,"vot_f":0,"vot_t":0,"perc_r":"0"},{"com":3,"dt_com":20251123230000,"enti_p":0,"enti_t":2,"perc":"0","vot_m":0,"vot_f":0,"vot_t":0,"perc_r":"0"},{"com":4,"dt_com":20251124150000,"enti_p":0,"enti_t":2,"perc":"0","vot_m":0,"vot_f":0,"vot_t":0,"perc_r":"0"}]}]}}
