{"int":{"st":"ESERCIZIO","t_ele":"Regionali Speciali","f_elet":"SCRUTINI","dt_ele":20251123000000,"l_terr":"CIRCOSCRIZIONE","area":"I","desc_circ":"TARANTO","cod_circ":78,"ele_m":0,"ele_f":0,"ele_t":483469,"vot_m":0,"vot_f":0,"vot_t":0,"perc_vot":"0","sz_pres":171,"sz_cons":169,"sz_tot":543,"fine_rip":"N","sk_bianche":0,"sk_nulle":0,"sk_contestate":0,"tot_vot_cand":47453,"tot_vot_lis":43196,"sg_spett_c":3,"sg_ass_c":0,"non_valid":null,"dt_agg":20251124181652,"data_prec_elez":20200920000000,"reg_sto":16,"circ_sto":78,"fine_pref":"N"},"note":null,"note_din":[],"cand":[{"cogn":"DECARO","nome":"ANTONIO","a_nome":null,"d_nasc":19700717000000,"l_nasc":"BARI","pos":3,"desc_lis_r":null,"img_lis_r":null,"voti":28540,"perc":"60,14","tot_vot_lis":25508,"perc_lis":"59,05","eletto":null,"sg_ass_c":0,"liste":[{"pos":6,"desc_lis_c":"PARTITO DEMOCRATICO - CANDIDATO PRESIDENTE DECARO","img_lis_c":"7-20251123000000-6-078.png","voti":10927,"perc":"25,30","seggi":0,"rif_nota":null},{"pos":2,"desc_lis_c":"DECARO PRESIDENTE","img_lis_c":"7-20251123000000-2-078.png","voti":5257,"perc":"12,17","seggi":0,"rif_nota":null},{"pos":7,"desc_lis_c":"MOVIMENTO 5 STELLE","img_lis_c":"7-20251123000000-7-078.png","voti":3554,"perc":"8,23","seggi":0,"rif_nota":null},{"pos":4,"desc_lis_c":"PER LA PUGLIA DECARO CANDIDATO PRESIDENTE","img_lis_c":"7-20251123000000-4-078.png","voti":2873,"perc":"6,65","seggi":0,"rif_nota":null},{"pos":5,"desc_lis_c":"ALLEANZA VERDI E SINISTRA","img_lis_c":"7-20251123000000-5-078.png","voti":1831,"perc":"4,24","seggi":0,"rif_nota":null},{"pos":8,"desc_lis_c":"AVANTI POPOLARI CON DECARO CANDIDATO PRESIDENTE","img_lis_c":"7-20251123000000-8-078.png","voti":1066,"perc":"2,47","seggi":0,"rif_nota":null}]},{"cogn":"LOBUONO","nome":"LUIGI","a_nome":null,"d_nasc":19550115000000,"l_nasc":"BARI","pos":4,"desc_lis_r":null,"img_lis_r":null,"voti":18475,"perc":"38,93","tot_vot_lis":17426,"perc_lis":"40,34","eletto":null,"sg_ass_c":0,"liste":[{"pos":11,"desc_lis_c":"FRATELLI D'ITALIA - GIORGIA MELONI","img_lis_c":"7-20251123000000-11-078.png","voti":8625,"perc":"19,97","seggi":0,"rif_nota":null},{"pos":9,"desc_lis_c":"FORZA ITALIA - BERLUSCONI - PPE - LOBUONO PRESIDENTE","img_lis_c":"7-20251123000000-9-078.png","voti":4587,"perc":"10,62","seggi":0,"rif_nota":null},{"pos":12,"desc_lis_c":"LEGA PUGLIA","img_lis_c":"7-20251123000000-12-078.png","voti":3627,"perc":"8,40","seggi":0,"rif_nota":null},{"pos":10,"desc_lis_c":"NOI MODERATI - CIVICI PER LOBUONO","img_lis_c":"7-20251123000000-10-078.png","voti":530,"perc":"1,23","seggi":0,"rif_nota":null},{"pos":3,"desc_lis_c":"LA PUGLIA CON NOI","img_lis_c":"7-20251123000000-3-078.png","voti":57,"perc":"0,13","seggi":0,"rif_nota":null}]},{"cogn":"DONNO","nome":"ADA","a_nome":null,"d_nasc":19471228000000,"l_nasc":"SURBO","pos":1,"desc_lis_r":null,"img_lis_r":null,"voti":316,"perc":"0,67","tot_vot_lis":188,"perc_lis":"0,44","eletto":null,"sg_ass_c":0,"liste":[{"pos":13,"desc_lis_c":"PUGLIA PACIFISTA E POPOLARE","img_lis_c":"7-20251123000000-13-078.png","voti":188,"perc":"0,44","seggi":0,"rif_nota":null}]},{"cogn":"MANGANO","nome":"SABINO","a_nome":null,"d_nasc":19750201000000,"l_nasc":"BARI","pos":2,"desc_lis_r":null,"img_lis_r":null,"voti":122,"perc":"0,26","tot_vot_lis":74,"perc_lis":"0,17","eletto":null,"sg_ass_c":0,"liste":[{"pos":1,"desc_lis_c":"ALLEANZA CIVICA PER LA PUGLIA","img_lis_c":"7-20251123000000-1-078.png","voti":74,"perc":"0,17","seggi":0,"rif_nota":null}]}]}
